crh/__init__.py
crh/main.py
mdul/__init__.py
mdul/main.py
crh-0.0.1.dist-info/METADATA
crh-0.0.1.dist-info/WHEEL
crh-0.0.1.dist-info/entry_points.txt
crh-0.0.1.dist-info/top_level.txt
crh-0.0.1.dist-info/RECORD
